uwsgi_chunked/__init__.py
uwsgi_chunked/chunked.py
uwsgi_chunked/version.py
uwsgi_chunked-0.1.8.dist-info/LICENSE
uwsgi_chunked-0.1.8.dist-info/METADATA
uwsgi_chunked-0.1.8.dist-info/WHEEL
uwsgi_chunked-0.1.8.dist-info/top_level.txt
uwsgi_chunked-0.1.8.dist-info/RECORD
