Metadata-Version: 2.1
Name: uwsgi-chunked
Version: 0.1.8
Summary: Allow WSGI applications to use Transfer-Encoding: chunked under uWSGI.
Home-page: http://github.com/btimby/uwsgi-chunked/
Author: Ben Timby
Author-email: btimby@gmail.com
Maintainer: Ben Timby
Maintainer-email: btimby@gmail.com
License: MIT
Platform: UNKNOWN
Classifier: Development Status :: 4 - Beta
Classifier: Intended Audience :: Developers
Classifier: Operating System :: OS Independent
Classifier: Programming Language :: Python :: 2
Classifier: Programming Language :: Python :: 3
Classifier: Topic :: Software Development :: Libraries :: Python Modules
License-File: LICENSE
